cleaners-0.1.0.dist-info/METADATA
cleaners-0.1.0.dist-info/WHEEL
cleaners-0.1.0.dist-info/entry_points.txt
distilabel_dataset_generator/__init__.py
distilabel_dataset_generator/_tabbedinterface.py
distilabel_dataset_generator/app.py
distilabel_dataset_generator/apps/__init__.py
distilabel_dataset_generator/apps/base.py
distilabel_dataset_generator/apps/eval.py
distilabel_dataset_generator/apps/faq.py
distilabel_dataset_generator/apps/sft.py
distilabel_dataset_generator/apps/textcat.py
distilabel_dataset_generator/constants.py
distilabel_dataset_generator/pipelines/__init__.py
distilabel_dataset_generator/pipelines/base.py
distilabel_dataset_generator/pipelines/embeddings.py
distilabel_dataset_generator/pipelines/eval.py
distilabel_dataset_generator/pipelines/sft.py
distilabel_dataset_generator/pipelines/textcat.py
distilabel_dataset_generator/utils.py
cleaners-0.1.0.dist-info/RECORD
