Metadata-Version: 2.1
Name: cleaners
Version: 0.1.0
Summary: Build datasets using natural language
Author-Email: davidberenstein1957 <david.m.berenstein@gmail.com>
License: Apache 2
Requires-Python: <3.13,>=3.10
Requires-Dist: distilabel[argilla,hf-inference-endpoints,instructor,outlines]>=1.4.1
Requires-Dist: gradio[oauth]<5.0.0
Requires-Dist: transformers>=4.44.2
Requires-Dist: sentence-transformers>=3.2.0
Requires-Dist: model2vec>=0.2.4
Requires-Dist: gradio-huggingfacehub-search>=0.0.7
Requires-Dist: argilla>=2.4.0
